{"name":"h1","plugin-id":"Sprite","sid":983954485985941,"isGlobal":false,"instanceVariables":[],"behaviorTypes":[{"behaviorId":"solid","name":"Твердый","sid":149770137927304}],"effectTypes":[],"animations":{"items":[{"frames":[{"width":16,"height":16,"originX":0,"originY":0,"originalSource":"","exportFormat":"png","exportQuality":0.8,"imageSpriteId":11,"duration":1}],"sid":719612595712244,"name":"Animation 1","isLooping":false,"isPingPong":false,"repeatCount":1,"repeatTo":0,"speed":5}],"subfolders":[]}}